MANIFEST.in
README.md
setup.cfg
setup.py
ansibler/__init__.py
ansibler/run.py
ansibler.egg-info/PKG-INFO
ansibler.egg-info/SOURCES.txt
ansibler.egg-info/dependency_links.txt
ansibler.egg-info/entry_points.txt
ansibler.egg-info/requires.txt
ansibler.egg-info/top_level.txt
ansibler/args/__init__.py
ansibler/args/cmd.py
ansibler/compatibility/__init__.py
ansibler/compatibility/chart.py
ansibler/exceptions/__init__.py
ansibler/exceptions/ansibler.py
ansibler/molecule_test/__init__.py
ansibler/molecule_test/parse.py
ansibler/platforms/__init__.py
ansibler/platforms/platform_map.py
ansibler/platforms/populate.py
ansibler/role_dependencies/__init__.py
ansibler/role_dependencies/cache.py
ansibler/role_dependencies/dependencies.py
ansibler/role_dependencies/galaxy.py
ansibler/role_dependencies/role_info.py
ansibler/utils/__init__.py
ansibler/utils/files.py
ansibler/utils/help.py
ansibler/utils/subprocesses.py
test/__init__.py
test/test_args/__init__.py
test/test_args/test_cmd_args.py
test/test_molecule/__init__.py
test/test_molecule/test_parse.py
test/test_role_dependencies/__init__.py
test/test_role_dependencies/test_dependencies.py
test/test_role_dependencies/test_galaxy.py
test/test_role_dependencies/test_role_info.py
test/test_utils/__init__.py
test/test_utils/test_files.py
test/test_utils/test_subprocesses.py