Metadata-Version: 1.1
Name: ansibler
Version: 0.2.4
Summary: Generate JSON data that describes the dependencies of an Ansible playbook/role. Also, automatically generate OS compatibility charts using Molecule.
Home-page: https://gitlab.com/megabyte-labs/python/ansibler/
Author: Renny Montero
Author-email: rennym19@gmail.com
License: MIT
Download-URL: https://gitlab.com/megabyte-labs/python/ansibler/archive/v_0_2_4.tar.gz
Keywords: ANSIBLE,DEPENDENCY,ROLE,MOLECULE,CHARTS,TEST
Platform: UNKNOWN
Classifier: Development Status :: 4 - Beta
Classifier: Intended Audience :: Developers
Classifier: Topic :: Software Development :: Build Tools
Classifier: License :: OSI Approved :: MIT License
Classifier: Programming Language :: Python :: 3
Classifier: Programming Language :: Python :: 3.4
Classifier: Programming Language :: Python :: 3.5
Classifier: Programming Language :: Python :: 3.6
Classifier: Programming Language :: Python :: 3.7
Classifier: Programming Language :: Python :: 3.8
Classifier: Programming Language :: Python :: 3.9
